{"cameraMode":{"drawMode":0,"name":"Shaded","section":"Shading Mode"},"sceneLighting":true,"audioPlay":false,"sceneViewState":{"m_AlwaysRefresh":false,"showFog":true,"showSkybox":true,"showFlares":true,"showImageEffects":true,"showParticleSystems":true,"showVisualEffectGraphs":true,"m_FxEnabled":true},"in2DMode":false,"pivot":{"x":-1.2069997787475587,"y":2.1599998474121095,"z":1.7074997425079346},"rotation":{"x":-0.1056094616651535,"y":0.8853555917739868,"z":-0.37988123297691347,"w":-0.2461787462234497},"size":12.12435531616211,"orthographic":false}